pinlog
