Metadata-Version: 2.1
Name: pinlog
Version: 0.3.2
Summary: PinLog is a powerful driver and library integrated several logging systems.
Home-page: https://github.com/superoutput/pinlog
Author: Savage Lasa
Author-email: superoutput@gmail.com
License: Savage
Keywords: python log driver library integrated integration logging system
Platform: UNKNOWN
